Workbook

Sheet INPUT MASTER
A1: FINANCIAL MANAGEMENT - INPUT MASTER BULANAN
A3: PERIODE ANGGARAN | E3: 🍩 PROPORSI PEMASUKAN | I3: 🍩 PROPORSI PENGELUARAN (THE BIG 3)
A4: Bulan | B4: September | C4: Tahun | D4: 2026 | E4: [ DIAGRAM DONAT: SUMBER PEMASUKAN ] | I4: [ DIAGRAM DONAT: KATEGORI PENGELUARAN ] (Tempat Tinggal, Transportasi, Makanan, Gaya Hidup)
A6: RANGKUMAN ARUS KAS BULANAN
A7: 1. Total Pendapatan | D7: =SUM(H14:H19) -> 0
A8: 2. Total Pengeluaran (Grant Sabatier) | D8: =SUM(M14:M35) -> 0
A9: 3. Total Investasi | D9: =SUM(H23:H27) -> 0
A10: 4. Total Cicilan & Hutang | D10: =SUM(H31:H35) -> 0
A11: 5. Sisa Arus Kas / Tabungan Bersih | D11: =D7-(D8+D9+D10) -> 0
A12: Rasio Tabungan & Investasi | D12: =IFERROR((D9+D11)/D7, 0) -> 0 | E12: DAFTAR PEMASUKAN (INCOME) | I12: DAFTAR PENGELUARAN BULANAN (GRANT SABATIER)
I13: No | J13: Pilar Kategori | K13: Sub-Kategori / Pos Pengeluaran | L13: Tipe | M13: Nominal (Rp)
E14: 1 | F14: Gaji Pokok / Uang Saku Utama | G14: Gaji Utama | H14: 0 | I14: 1 | J14: 🏠 Tempat Tinggal | K14: Sewa Kos / Kontrakan / IPL | L14: Kebutuhan | M14: 0
A15: 📊 DIAGRAM ARUS KAS BULANAN | E15: 2 | F15: Tunjangan / Insentif / Bonus | G15: Gaji Utama | H15: 0 | I15: 2 | J15: 🏠 Tempat Tinggal | K15: Listrik & Token PLN | L15: Kebutuhan | M15: 0
A16: [ AREA GRAFIK BATANG: ARUS KAS BULANAN ] (Menampilkan visualisasi perbandingan Pendapatan, Pengeluaran, Investasi, dan Cicilan) | E16: 3 | F16: Freelance / Side Project | G16: Freelance | H16: 0 | I16: 3 | J16: 🏠 Tempat Tinggal | K16: Air & Gas Tabung | L16: Kebutuhan | M16: 0
E17: 4 | F17: Bisnis / Jualan / UMKM | G17: Bisnis | H17: 0 | I17: 4 | J17: 🏠 Tempat Tinggal | K17: Internet Wifi / Kuota Data | L17: Kebutuhan | M17: 0
E18: 5 | F18: Passive Income (Dividen/Bunga/Sewa) | G18: Passive Income | H18: 0 | I18: 5 | J18: 🏠 Tempat Tinggal | K18: Perlengkapan & Kebersihan Rumah | L18: Kebutuhan | M18: 0
E19: 6 | F19: Lain-lain / Hadiah / Transfer | G19: Lainnya | H19: 0 | I19: 6 | J19: 🚗 Transportasi | K19: Bahan Bakar (Bensin / Pertalite / Pertamax) | L19: Kebutuhan | M19: 0
I20: 7 | J20: 🚗 Transportasi | K20: Transportasi Umum / Ojek Online (Gojek/Grab) | L20: Kebutuhan | M20: 0
E21: ALOKASI INVESTASI BULANAN | I21: 8 | J21: 🚗 Transportasi | K21: Parkir, Tol & Cuci Kendaraan | L21: Kebutuhan | M21: 0
E22: No | F22: Instrumen Investasi | G22: Kategori Aset | H22: Nominal (Rp) | I22: 9 | J22: 🚗 Transportasi | K22: Perawatan, Servis & Ganti Oli | L22: Kebutuhan | M22: 0
E23: 1 | F23: Reksa Dana (Pasar Uang / Obligasi) | G23: Pasar Uang | H23: 0 | I23: 10 | J23: 🍲 Makanan & Minuman | K23: Belanja Bahan Makanan Pokok (Pasar/Supermarket) | L23: Kebutuhan | M23: 0
E24: 2 | F24: Saham / ETF (IHSG / Global) | G24: Ekuitas | H24: 0 | I24: 11 | J24: 🍲 Makanan & Minuman | K24: Makan Harian di Luar (Warteg/Kantin) | L24: Kebutuhan | M24: 0
E25: 3 | F25: Emas Fisik / Logam Mulia Digital | G25: Komoditas | H25: 0 | I25: 12 | J25: 🍲 Makanan & Minuman | K25: Kopi Susu, Camilan & Jajan Sore (Latte Factor) | L25: Keinginan | M25: 0
E26: 4 | F26: Surat Berharga Negara (SBN / Sukuk) | G26: Pendapatan Tetap | H26: 0 | I26: 13 | J26: 🍲 Makanan & Minuman | K26: Pesan Antar Makanan (ShopeeFood/GoFood) | L26: Keinginan | M26: 0
E27: 5 | F27: Aset Kripto / P2P / Lainnya | G27: Aset Alternatif | H27: 0 | I27: 14 | J27: 💊 Kesehatan | K27: BPJS Kesehatan / Asuransi | L27: Kebutuhan | M27: 0
I28: 15 | J28: 💊 Kesehatan | K28: Obat-obatan, Vitamin & Medis | L28: Kebutuhan | M28: 0
E29: PELACAK CICILAN & HUTANG BERJALAN | I29: 16 | J29: 💊 Kesehatan | K29: Skincare & Perawatan Tubuh | L29: Kebutuhan | M29: 0
E30: No | F30: Nama Cicilan / Kredit | G30: Sisa Tenor | H30: Cicilan / Bulan | I30: 17 | J30: 🎉 Gaya Hidup | K30: Langganan Digital (Netflix/Spotify/iCloud) | L30: Keinginan | M30: 0
E31: 1 | F31: KPR / Sewa Hunian Jangka Panjang | G31: 120 Bulan | H31: 0 | I31: 18 | J31: 🎉 Gaya Hidup | K31: Nongkrong, Hiburan & Bioskop | L31: Keinginan | M31: 0
E32: 2 | F32: Kredit Kendaraan (Motor/Mobil) | G32: 24 Bulan | H32: 0 | I32: 19 | J32: 🎉 Gaya Hidup | K32: Belanja Pakaian & Fashion Pribadi | L32: Keinginan | M32: 0
E33: 3 | F33: Kartu Kredit / Paylater | G33: Lunas Bulan Ini | H33: 0 | I33: 20 | J33: 🤝 Sosial & Donasi | K33: Uang Orang Tua / Keluarga (Sandwich Gen) | L33: Kebutuhan | M33: 0
E34: 4 | F34: Cicilan Gadget / Elektronik | G34: 6 Bulan | H34: 0 | I34: 21 | J34: 🤝 Sosial & Donasi | K34: Zakat, Infaq, Sedekah & Hadiah Teman | L34: Kebutuhan | M34: 0
E35: 5 | F35: Pinjaman Lainnya | G35: 12 Bulan | H35: 0 | I35: 22 | J35: 📦 Lain-lain | K35: Pengeluaran Tak Terduga / Darurat | L35: Kebutuhan | M35: 0

Sheet OVERVIEW SATU TAHUN
A1: OVERVIEW TAHUNAN - LAPORAN ARUS KAS 12 BULAN
B3: TOTAL PENDAPATAN 1 TAHUN | G3: TOTAL PENGELUARAN 1 TAHUN | L3: TOTAL INVESTASI & TABUNGAN
B4: =SUM(B10:M10) -> 0 | G4: =SUM(B18:M18) -> 0 | L4: =SUM(B19:M19)+SUM(B21:M21) -> 0
A8: Kategori Arus Kas | B8: Jan | C8: Feb | D8: Mar | E8: Apr | F8: Mei | G8: Jun | H8: Jul | I8: Agu | J8: Sep | K8: Okt | L8: Nov | M8: Des | N8: TOTAL TAHUN | O8: RATA-RATA / BLN
A9: 1. TOTAL PENDAPATAN (INCOME)
A10: - Pemasukan Kas Bersih | B10: 0 | C10: 0 | D10: 0 | E10: 0 | F10: 0 | G10: 0 | H10: 0 | I10: 0 | J10: ='INPUT MASTER'!D7 -> 0 | K10: 0 | L10: 0 | M10: 0 | N10: =SUM(B10:M10) -> 0 | O10: =AVERAGE(B10:M10) -> 0
A11: 2. PENGELUARAN BULANAN (EXPENSES)
A12: - 🏠 Tempat Tinggal & Utilitas | B12: 0 | C12: 0 | D12: 0 | E12: 0 | F12: 0 | G12: 0 | H12: 0 | I12: 0 | J12: =SUM('INPUT MASTER'!M14:M18) -> 0 | K12: 0 | L12: 0 | M12: 0 | N12: =SUM(B12:M12) -> 0 | O12: =AVERAGE(B12:M12) -> 0
A13: - 🚗 Transportasi Harian | B13: 0 | C13: 0 | D13: 0 | E13: 0 | F13: 0 | G13: 0 | H13: 0 | I13: 0 | J13: =SUM('INPUT MASTER'!M19:M22) -> 0 | K13: 0 | L13: 0 | M13: 0 | N13: =SUM(B13:M13) -> 0 | O13: =AVERAGE(B13:M13) -> 0
A14: - 🍲 Makanan & Minuman | B14: 0 | C14: 0 | D14: 0 | E14: 0 | F14: 0 | G14: 0 | H14: 0 | I14: 0 | J14: =SUM('INPUT MASTER'!M23:M26) -> 0 | K14: 0 | L14: 0 | M14: 0 | N14: =SUM(B14:M14) -> 0 | O14: =AVERAGE(B14:M14) -> 0
A15: - 💊 Kesehatan & Perawatan | B15: 0 | C15: 0 | D15: 0 | E15: 0 | F15: 0 | G15: 0 | H15: 0 | I15: 0 | J15: =SUM('INPUT MASTER'!M27:M29) -> 0 | K15: 0 | L15: 0 | M15: 0 | N15: =SUM(B15:M15) -> 0 | O15: =AVERAGE(B15:M15) -> 0
A16: - 🎉 Gaya Hidup, Sosial & Lainnya | B16: 0 | C16: 0 | D16: 0 | E16: 0 | F16: 0 | G16: 0 | H16: 0 | I16: 0 | J16: =SUM('INPUT MASTER'!M30:M35) -> 0 | K16: 0 | L16: 0 | M16: 0 | N16: =SUM(B16:M16) -> 0 | O16: =AVERAGE(B16:M16) -> 0
A17: TOTAL PENGELUARAN | B17: =SUM(B12:B16) -> 0 | C17: =SUM(C12:C16) -> 0 | D17: =SUM(D12:D16) -> 0 | E17: =SUM(E12:E16) -> 0 | F17: =SUM(F12:F16) -> 0 | G17: =SUM(G12:G16) -> 0 | H17: =SUM(H12:H16) -> 0 | I17: =SUM(I12:I16) -> 0 | ... M17: =SUM(M12:M16) -> 0 | N17: =SUM(B17:M17) -> 0 | O17: =AVERAGE(B17:M17) -> 0
A18: 3. TOTAL INVESTASI (ASSETS)
A19: - Reksadana, Saham, Emas, SBN | B19: 0 | C19: 0 | D19: 0 | E19: 0 | F19: 0 | G19: 0 | H19: 0 | I19: 0 | J19: ='INPUT MASTER'!D9 -> 0 | K19: 0 | L19: 0 | M19: 0 | N19: =SUM(B19:M19) -> 0 | O19: =AVERAGE(B19:M19) -> 0
A20: 4. TOTAL CICILAN & HUTANG
A21: - Cicilan Berjalan | B21: 0 | C21: 0 | D21: 0 | E21: 0 | F21: 0 | G21: 0 | H21: 0 | I21: 0 | J21: ='INPUT MASTER'!D10 -> 0 | K21: 0 | L21: 0 | M21: 0 | N21: =SUM(B21:M21) -> 0 | O21: =AVERAGE(B21:M21) -> 0
A22: 5. SISA ARUS KAS BERSIH (NET CASHFLOW) | B22: =B10-(B17+B19+B21) -> 0 | C22: =C10-(C17+C19+C21) -> 0 | D22: =D10-(D17+D19+D21) -> 0 | E22: =E10-(E17+E19+E21) -> 0 | F22: =F10-(F17+F19+F21) -> 0 | G22: =G10-(G17+G19+G21) -> 0 | H22: =H10-(H17+H19+H21) -> 0 | I22: =I10-(I17+I19+I21) -> 0 | ... M22: =M10-(M17+M19+M21) -> 0 | N22: =SUM(B22:M22) -> 0 | O22: =AVERAGE(B22:M22) -> 0
